odoo/addons/ssi_hr_expense/README.rst
odoo/addons/ssi_hr_expense/__init__.py
odoo/addons/ssi_hr_expense/__manifest__.py
odoo/addons/ssi_hr_expense/menu.xml
odoo/addons/ssi_hr_expense/demo/hr_expense_type_demo.xml
odoo/addons/ssi_hr_expense/demo/product_category_demo.xml
odoo/addons/ssi_hr_expense/demo/product_product_demo.xml
odoo/addons/ssi_hr_expense/models/__init__.py
odoo/addons/ssi_hr_expense/models/hr_expense_type.py
odoo/addons/ssi_hr_expense/models/hr_expense_type_product.py
odoo/addons/ssi_hr_expense/models/hr_expense_type_product_category.py
odoo/addons/ssi_hr_expense/security/ir.model.access.csv
odoo/addons/ssi_hr_expense/security/ir_module_category_data.xml
odoo/addons/ssi_hr_expense/security/res_group_data.xml
odoo/addons/ssi_hr_expense/static/description/icon.png
odoo/addons/ssi_hr_expense/static/description/icon_timesheet.png
odoo/addons/ssi_hr_expense/views/hr_expense_type_product_category_views.xml
odoo/addons/ssi_hr_expense/views/hr_expense_type_product_views.xml
odoo/addons/ssi_hr_expense/views/hr_expense_type_views.xml
odoo14_addon_ssi_hr_expense-14.0.1.3.0.dist-info/METADATA
odoo14_addon_ssi_hr_expense-14.0.1.3.0.dist-info/WHEEL
odoo14_addon_ssi_hr_expense-14.0.1.3.0.dist-info/top_level.txt
odoo14_addon_ssi_hr_expense-14.0.1.3.0.dist-info/RECORD
